openai_cost_tracker/__init__.py
openai_cost_tracker/estimator.py
openai_cost_tracker/utils.py
openai_cost_tracker-0.5.dist-info/METADATA
openai_cost_tracker-0.5.dist-info/WHEEL
openai_cost_tracker-0.5.dist-info/top_level.txt
openai_cost_tracker-0.5.dist-info/RECORD
