Metadata-Version: 2.1
Name: openai_cost_tracker
Version: 0.5
Home-page: https://github.com/ruoyuxie/openai-cost-tracker
Author: Roy Xie
Author-email: royx252@gmail.com
Requires-Dist: tiktoken ==0.5.2
Requires-Dist: lorem-text ==2.1
Requires-Dist: openai ==0.28.0
